rache/version.py
rache/utils.py
rache/__init__.py
rache-0.3.1.dist-info/RECORD
rache-0.3.1.dist-info/top_level.txt
rache-0.3.1.dist-info/pydist.json
rache-0.3.1.dist-info/WHEEL
rache-0.3.1.dist-info/DESCRIPTION.rst
rache-0.3.1.dist-info/METADATA
