Metadata-Version: 2.0
Name: rache
Version: 0.3.1
Summary: A scheduler backed by Redis with a very simple interface
Home-page: https://github.com/brutasse/rache
Author: Bruno Renié
Author-email: bruno@renie.fr
License: BSD
Platform: UNKNOWN
Classifier: Development Status :: 4 - Beta
Classifier: Environment :: Web Environment
Classifier: Intended Audience :: Developers
Classifier: Natural Language :: English
Classifier: Programming Language :: Python
Classifier: Programming Language :: Python :: 2
Classifier: Programming Language :: Python :: 2.6
Classifier: Programming Language :: Python :: 2.7
Classifier: Programming Language :: Python :: 3
Classifier: Programming Language :: Python :: 3.2
Classifier: Programming Language :: Python :: 3.3
Requires-Dist: hiredis
Requires-Dist: redis
